{
    "No respetar el derecho de via":2891,
    "No atender el control del vehiculo": 2964,
    "Exceso de velocidad":859,
    "No obedecer las luces del semaforo":178,
    "Violaciones del peaton":488,
    "Conducir bajo la ingestion de bebidas alcoholicas":164,
    "Adelantamiento indebido":570,
    "Maniobra de marcha atras":188,
    "Estacionamiento inadecuado":28,
    "Violaciones de los conductores de ciclos":23,
    "Animales sueltos":301,
    "Desperfectos tecnicos":636,
    "Conductores que violan derecho del peaton":13,
    "Transportacion masiva":27,
    "Otros":518
}